huifikator/__init__.py
huifikator/lib.py
huifikator-0.1.0.dist-info/WHEEL
huifikator-0.1.0.dist-info/METADATA
huifikator-0.1.0.dist-info/RECORD
