Metadata-Version: 2.1
Name: huifikator
Version: 0.1.0
Summary: Lexical reduplication library
Author: CatCoderr
Author-email: catcoderr@gmail.com
Requires-Python: >=3.9,<4.0
Classifier: Programming Language :: Python :: 3
Classifier: Programming Language :: Python :: 3.10
Classifier: Programming Language :: Python :: 3.9
